{
  "vehicle": "F4_T421_2022",

  "AB_standard": 0.4,

  "models": {

    "with_gurney": {

      "AB_wing_model": {
        "description": "Modelo de Aero Balance (AB) en funci贸n de FW y RW con gurney instalado.",
        "variables": {
          "fw": { "unit": "deg", "range": [3, 7] },
          "rw": { "unit": "deg", "range": [2, 21] }
        },
        "coefficients": [
          -0.0883829261,
          -0.0346345637,
          0.098125,
          0.000615516063,
          -0.0030125,
          -0.00000000000000000520
        ],
        "powers": [
          { "fw": 0, "rw": 0 },
          { "fw": 0, "rw": 1 },
          { "fw": 1, "rw": 0 },
          { "fw": 0, "rw": 2 },
          { "fw": 2, "rw": 0 },
          { "fw": 1, "rw": 1 }
        ]
      },

      "AB_height_model": {
        "description": "Modelo de Aero Balance (AB) en funci贸n de FRH y RRH con gurney instalado.",
        "variables": {
          "frh": { "unit": "mm", "range": [20, 75] },
          "rrh": { "unit": "mm", "range": [5, 25] }
        },
        "coefficients": [
          -0.0677565097,
          -0.0135504612,
          0.00774081416,
          -0.00000107403340,
          -0.000000277600974,
          0.00000110798807
        ],
        "powers": [
          { "frh": 0, "rrh": 0 },
          { "frh": 1, "rrh": 0 },
          { "frh": 0, "rrh": 1 },
          { "frh": 2, "rrh": 0 },
          { "frh": 0, "rrh": 2 },
          { "frh": 1, "rrh": 1 }
        ]
      }
    },

    "without_gurney": {

      "AB_wing_model": {
        "description": "Modelo de Aero Balance (AB) en funci贸n de FW y RW sin gurney.",
        "variables": {
          "fw": { "unit": "deg", "range": [3, 7] },
          "rw": { "unit": "deg", "range": [2, 21] }
        },
        "coefficients": [
          -0.358203618,
          -0.0346222735,
          0.0712732143,
          0.00061686413,
          0.00036875,
          -0.0000107142857
        ],
        "powers": [
          { "fw": 0, "rw": 0 },
          { "fw": 0, "rw": 1 },
          { "fw": 1, "rw": 0 },
          { "fw": 0, "rw": 2 },
          { "fw": 2, "rw": 0 },
          { "fw": 1, "rw": 1 }
        ]
      },

      "AB_height_model": {
        "description": "Modelo de Aero Balance (AB) en funci贸n de FRH y RRH sin gurney.",
        "variables": {
          "frh": { "unit": "mm", "range": [20, 75] },
          "rrh": { "unit": "mm", "range": [5, 25] }
        },
        "coefficients": [
          -0.378539843,
          0.00774081416,
          -0.0135504612,
          -0.000000277600974,
          -0.00000107403340,
          0.00000110798807
        ],
        "powers": [
          { "frh": 0, "rrh": 0 },
          { "frh": 0, "rrh": 1 },
          { "frh": 1, "rrh": 0 },
          { "frh": 0, "rrh": 1 },
          { "frh": 2, "rrh": 0 },
          { "frh": 1, "rrh": 1 }
        ]
      }
    }
  }
}
